invenio_app/__init__.py
invenio_app/celery.py
invenio_app/cli.py
invenio_app/config.py
invenio_app/ext.py
invenio_app/factory.py
invenio_app/helpers.py
invenio_app/limiter.py
invenio_app/wsgi.py
invenio_app/wsgi_rest.py
invenio_app/wsgi_ui.py
invenio_app-2.3.0.dist-info/licenses/AUTHORS.rst
invenio_app-2.3.0.dist-info/licenses/LICENSE
invenio_app-2.3.0.dist-info/METADATA
invenio_app-2.3.0.dist-info/WHEEL
invenio_app-2.3.0.dist-info/entry_points.txt
invenio_app-2.3.0.dist-info/top_level.txt
invenio_app-2.3.0.dist-info/RECORD
