Metadata-Version: 2.4
Name: invenio-app
Version: 2.3.0
Summary: WSGI, Celery and CLI applications for Invenio flavours.
Home-page: https://github.com/inveniosoftware/invenio-app
Author: CERN
Author-email: info@inveniosoftware.org
License: MIT
Keywords: invenio applications
Platform: any
Classifier: Development Status :: 5 - Production/Stable
Requires-Python: >=3.7
License-File: LICENSE
License-File: AUTHORS.rst
Requires-Dist: flask>=3.1.0
Requires-Dist: flask-limiter<3,>=2
Requires-Dist: flask-shell-ipython>=0.3.1
Requires-Dist: flask-talisman<1.0,>=0.3.2
Requires-Dist: invenio-base<3.0.0,>=2.2.0
Requires-Dist: invenio-cache<3.0.0,>=2.0.0
Requires-Dist: invenio-celery<3.0.0,>=2.0.0
Requires-Dist: invenio-config<2.0.0,>=1.0.0
Requires-Dist: uritools>=1.0.1
Provides-Extra: tests
Requires-Dist: pytest-black-ng>=0.4.0; extra == "tests"
Requires-Dist: pytest-invenio<4.0.0,>=3.0.0; extra == "tests"
Requires-Dist: mock>=4.0.0; extra == "tests"
Requires-Dist: sphinx<6,>=5.0; extra == "tests"
Dynamic: license-file
